{
  "cookies": [
    {
      "name": "JSESSIONID",
      "value": "182C863C7A6F2A8A6A274C358E36C764",
      "domain": "wiki.suncaper.net",
      "path": "/",
      "expires": -1,
      "httpOnly": true,
      "secure": false,
      "sameSite": "Lax"
    }
  ],
  "origins": [
    {
      "origin": "https://wiki.suncaper.net",
      "localStorage": [
        {
          "name": "confluence.scujj.sidebar.width",
          "value": "285"
        },
        {
          "name": "dashboard.scujj.route.last",
          "value": "all-updates"
        },
        {
          "name": "atlassian-analytics.confluence.lock",
          "value": "null"
        },
        {
          "name": "atst.healthcheck.sensors.page-protocols",
          "value": "-5v0af5"
        }
      ]
    }
  ]
}